client/__init__.py
client/client_.py
client/client/__init__.py
client/client/main_window.py
client/client/transport.py
client/common/__init__.py
client/common/decos.py
client/common/descryptors.py
client/common/errors.py
client/common/metaclasses.py
client/common/utils.py
client/common/variables.py
client/databases/__init__.py
client/databases/database.py
client/doc/__init__.py
client/doc/source/__init__.py
client/doc/source/conf.py
client/forms_gui/__init__.py
client/forms_gui/add_contact.py
client/forms_gui/del_contact.py
client/forms_gui/main_window_conv.py
client/forms_gui/start_dialog.py
client/logs/__init__.py
client/logs/client_log_config.py
client/test_unit/__init__.py
client_messenger_prog-0.1.dist-info/METADATA
client_messenger_prog-0.1.dist-info/WHEEL
client_messenger_prog-0.1.dist-info/top_level.txt
client_messenger_prog-0.1.dist-info/RECORD
