Metadata-Version: 2.1
Name: client-messenger-prog
Version: 0.1
Summary: Client packet
Author: Pavlovich
Author-email: palbimov@yandex.ru
License: UNKNOWN
Platform: UNKNOWN
Requires-Dist: PyQt5
Requires-Dist: sqlalchemy
Requires-Dist: pycryptodome
Requires-Dist: pycryptodomex
